createdryverail/__init__.py
createdryverail/dryveCode.py
createdryverail-2.5.7.dist-info/METADATA
createdryverail-2.5.7.dist-info/WHEEL
createdryverail-2.5.7.dist-info/top_level.txt
createdryverail-2.5.7.dist-info/RECORD
